MANIFEST.in
setup.cfg
setup.py
docs/index.rst
secure_sedge.egg-info/PKG-INFO
secure_sedge.egg-info/SOURCES.txt
secure_sedge.egg-info/dependency_links.txt
secure_sedge.egg-info/entry_points.txt
secure_sedge.egg-info/requires.txt
secure_sedge.egg-info/top_level.txt
sedge/README.md
sedge/__init__.py
sedge/cert_tasks.py
sedge/installers.py
sedge/main.py
sedge/models.py
sedge/sedge_client.py
sedge/version.txt
sedge/dns_providers/__init__.py
sedge/dns_providers/akamai.py
sedge/dns_providers/route53.py