Metadata-Version: 2.1
Name: secure-sedge
Version: 1.9.2
Summary: a helpful set of convocations to create certs
Home-page: https://bitbucket.org/dbuy/secure_sedge
Author: 2ps
Author-email: p.shingavi@yahoo.com
License: BSD
Classifier: Development Status :: 5 - Production/Stable
Classifier: Environment :: Console
Classifier: Intended Audience :: Developers
Classifier: Intended Audience :: System Administrators
Classifier: License :: OSI Approved :: BSD License
Classifier: Operating System :: POSIX
Classifier: Operating System :: Unix
Classifier: Operating System :: MacOS :: MacOS X
Classifier: Operating System :: Microsoft :: Windows
Classifier: Programming Language :: Python
Classifier: Programming Language :: Python :: 3
Classifier: Programming Language :: Python :: 3.6
Classifier: Programming Language :: Python :: 3.7
Classifier: Programming Language :: Python :: 3.8
Classifier: Topic :: Software Development
Classifier: Topic :: Software Development :: Build Tools
Classifier: Topic :: Software Development :: Libraries
Classifier: Topic :: Software Development :: Libraries :: Python Modules
Classifier: Topic :: System :: Software Distribution
Classifier: Topic :: System :: Systems Administration
Requires-Dist: raft>=1.4.1.2
Requires-Dist: boto3
Requires-Dist: sewer[route53]==0.8.2
Requires-Dist: pyyaml
Requires-Dist: colorlog
Requires-Dist: requests
Requires-Dist: cryptography>=41.0.7
Requires-Dist: pyjks; sys_platform != "win32"
Requires-Dist: pythonnet; sys_platform == "win32"
Requires-Dist: edgegrid-python
Requires-Dist: convocations
Requires-Dist: waddle
